blackbox_mpc/__init__.py
blackbox_mpc/dynamics_functions/__init__.py
blackbox_mpc/dynamics_functions/deterministic_mlp.py
blackbox_mpc/dynamics_handlers/__init__.py
blackbox_mpc/dynamics_handlers/system_dynamics_handler.py
blackbox_mpc/environment_utils/__init__.py
blackbox_mpc/environment_utils/environment_wrapper.py
blackbox_mpc/environment_utils/subprocess_env.py
blackbox_mpc/optimizers/__init__.py
blackbox_mpc/optimizers/cem.py
blackbox_mpc/optimizers/cma_es.py
blackbox_mpc/optimizers/optimizer_base.py
blackbox_mpc/optimizers/pi2.py
blackbox_mpc/optimizers/pso.py
blackbox_mpc/optimizers/random_search.py
blackbox_mpc/optimizers/spsa.py
blackbox_mpc/policies/__init__.py
blackbox_mpc/policies/model_based_base_policy.py
blackbox_mpc/policies/model_free_base_policy.py
blackbox_mpc/policies/mpc_policy.py
blackbox_mpc/policies/random_policy.py
blackbox_mpc/trajectory_evaluators/__init__.py
blackbox_mpc/trajectory_evaluators/deterministic.py
blackbox_mpc/trajectory_evaluators/evaluator_base.py
blackbox_mpc/utils/__init__.py
blackbox_mpc/utils/dynamics_learning.py
blackbox_mpc/utils/iterative_mpc.py
blackbox_mpc/utils/pendulum.py
blackbox_mpc/utils/recording.py
blackbox_mpc/utils/rollouts.py
blackbox_mpc/utils/transforms.py
tutorials/__init__.py
blackbox_mpc-0.3.dist-info/METADATA
blackbox_mpc-0.3.dist-info/WHEEL
blackbox_mpc-0.3.dist-info/top_level.txt
blackbox_mpc-0.3.dist-info/RECORD
